GooseHDF5/__init__.py
GooseHDF5/_version.py
GooseHDF5-0.27.0.dist-info/LICENSE
GooseHDF5-0.27.0.dist-info/METADATA
GooseHDF5-0.27.0.dist-info/WHEEL
GooseHDF5-0.27.0.dist-info/entry_points.txt
GooseHDF5-0.27.0.dist-info/top_level.txt
GooseHDF5-0.27.0.dist-info/RECORD
