Metadata-Version: 2.1
Name: GooseHDF5
Version: 0.27.0
Summary: Wrapper around h5py
Author-email: Tom de Geus <tom@geus.me>
Project-URL: Source, https://github.com/tdegeus/GooseHDF5
Classifier: License :: OSI Approved :: MIT License
Requires-Python: >=3.6
License-File: LICENSE
Requires-Dist: click
Requires-Dist: h5py
Requires-Dist: prettytable
Requires-Dist: pyyaml
Requires-Dist: termcolor
